weaviate_etl/__init__.py
weaviate_etl/exceptions.py
weaviate_etl/model.py
weaviate_etl/process_result.py
weaviate_etl/query.py
weaviate_etl/utilities.py
weaviate_etl/classification/__init__.py
weaviate_etl/classification/classification.py
weaviate_etl/classification/confidence.py
weaviate_etl/classification/run_classification.py
weaviate_etl/data/__init__.py
weaviate_etl/data/data.py
weaviate_etl/data/imports.py
weaviate_etl/data/parser.py
weaviate_etl/schema/__init__.py
weaviate_etl/schema/generate_schema.py
weaviate_etl/schema/schema.py
weaviate_etl-0.0.15.dist-info/METADATA
weaviate_etl-0.0.15.dist-info/WHEEL
weaviate_etl-0.0.15.dist-info/top_level.txt
weaviate_etl-0.0.15.dist-info/RECORD
